br_feriados_municipais/__init__.py
br_feriados_municipais/feriados_br.py
br_feriados_municipais-1.0.1.dist-info/LICENCE
br_feriados_municipais-1.0.1.dist-info/METADATA
br_feriados_municipais-1.0.1.dist-info/WHEEL
br_feriados_municipais-1.0.1.dist-info/top_level.txt
br_feriados_municipais-1.0.1.dist-info/RECORD
