Metadata-Version: 2.1
Name: br-feriados-municipais
Version: 1.0.1
Summary: Versão beta da biblioteca de feriados municipais.
Author: Luiz Fernando Teles Rodrigues
Author-email: euluizfernando2001@gmail.com
License: MIT License
Keywords: feriados br municipais brasil
License-File: LICENCE
Requires-Dist: datetime
